commitdb/__init__.py
commitdb/binding.py
commitdb/client.py
commitdb/ibis_backend.py
commitdb/lib/libcommitdb-linux-amd64.so
tests/__init__.py
tests/test_client.py
tests/test_ibis.py
commitdb-2.5.0.dist-info/METADATA
commitdb-2.5.0.dist-info/WHEEL
commitdb-2.5.0.dist-info/entry_points.txt
commitdb-2.5.0.dist-info/top_level.txt
commitdb-2.5.0.dist-info/RECORD
