Metadata-Version: 2.4
Name: commitdb
Version: 2.5.0
Summary: Python Client for CommitDB SQL Server
Author: CommitDB Contributors
License: Apache-2.0
Project-URL: Homepage, https://github.com/nickyhof/CommitDB
Project-URL: Documentation, https://github.com/nickyhof/CommitDB#readme
Project-URL: Repository, https://github.com/nickyhof/CommitDB
Keywords: database,sql,git,commitdb
Classifier: Development Status :: 3 - Alpha
Classifier: Intended Audience :: Developers
Classifier: License :: OSI Approved :: Apache Software License
Classifier: Programming Language :: Python :: 3
Classifier: Programming Language :: Python :: 3.10
Classifier: Programming Language :: Python :: 3.11
Classifier: Programming Language :: Python :: 3.12
Requires-Python: >=3.10
Provides-Extra: dev
Requires-Dist: pytest>=7.0; extra == "dev"
Provides-Extra: ibis
Requires-Dist: ibis-framework>=11.0; extra == "ibis"
Requires-Dist: pandas>=2.0; extra == "ibis"
